<?xml version="1.0" encoding="utf-8"?>
<LogPack account="Account470">
	<Account number="Account470">
		<PassWord>123456</PassWord>
		<InitialFunds>1000000</InitialFunds>
	</Account>
	<DailyLog date="2019-01-01">
		<Date>2019-01-01</Date>
		<BeginAvailable>1000000</BeginAvailable>
		<BeginHolding>EmptyHold
		</BeginHolding>
		<EndAvailable>1000000</EndAvailable>
		<EndHolding>EmptyHold
		</EndHolding>
	</DailyLog>
	<DailyLog date="2019-08-11">
		<date>2019-08-11</date>
		<BeginAvailable>1000000.0</BeginAvailable>
		<BeginHolding Hold="Hold"/>
		<EndAvailable>1000000.0</EndAvailable>
		<EndHolding Hold="Hold"/>
	</DailyLog>
	<DailyLog date="2019-08-12">
		<date>2019-08-12</date>
		<BeginAvailable>500746.47040000005</BeginAvailable>
		<BeginHolding Hold="Hold"/>
		<BuyOperation>
			<StockCode>002809</StockCode>
			<StockNumber>30100</StockNumber>
			<CostPrice>16.56</CostPrice>
			<OtherExpenses>797.5296</OtherExpenses>
			<Time>2019-08-12 09:57:30</Time>
		</BuyOperation>
		<EndAvailable>500746.47040000005</EndAvailable>
		<EndHolding Hold="Hold">
			<Stock>
				<StockCode>002809</StockCode>
				<StockNumber>30100.0</StockNumber>
				<CostPrice>16.56</CostPrice>
				<OtherExpenses>797.5295999999421</OtherExpenses>
			</Stock>
		</EndHolding>
	</DailyLog>
	<DailyLog date="2019-08-13">
		<date>2019-08-13</date>
		<BeginAvailable>500746.47040000005</BeginAvailable>
		<BeginHolding Hold="Hold">
			<Stock>
				<StockCode>002809</StockCode>
				<StockNumber>30100</StockNumber>
				<CostPrice>16.56</CostPrice>
				<OtherExpenses>797.5295999999421</OtherExpenses>
			</Stock>
		</BeginHolding>
		<SellOperation>
			<StockCode>002809</StockCode>
			<StockNumber>30100.0</StockNumber>
			<CostPrice>16.4</CostPrice>
			<OtherExpenses>0</OtherExpenses>
			<Time>2019-08-13 09:33:30</Time>
		</SellOperation>
		<EndAvailable>994386.4704</EndAvailable>
		<EndHolding Hold="Hold"/>
	</DailyLog>
	<DailyLog date="2019-08-14">
		<date>2019-08-14</date>
		<BeginAvailable>994386.4704</BeginAvailable>
		<BeginHolding Hold="Hold"/>
		<EndAvailable>994386.4704</EndAvailable>
		<EndHolding Hold="Hold"/>
	</DailyLog>
	<DailyLog date="2019-08-15">
		<date>2019-08-15</date>
		<BeginAvailable>994386.4704</BeginAvailable>
		<BeginHolding Hold="Hold"/>
		<EndAvailable>994386.4704</EndAvailable>
		<EndHolding Hold="Hold"/>
	</DailyLog>
	<DailyLog date="2019-08-16">
		<date>2019-08-16</date>
		<BeginAvailable>994386.4704</BeginAvailable>
		<BeginHolding Hold="Hold"/>
		<EndAvailable>994386.4704</EndAvailable>
		<EndHolding Hold="Hold"/>
	</DailyLog>
	<DailyLog date="2019-08-17">
		<date>2019-08-17</date>
		<BeginAvailable>994386.4704</BeginAvailable>
		<BeginHolding Hold="Hold"/>
		<EndAvailable>994386.4704</EndAvailable>
		<EndHolding Hold="Hold"/>
	</DailyLog>
	<DailyLog date="2019-08-18">
		<date>2019-08-18</date>
		<BeginAvailable>994386.4704</BeginAvailable>
		<BeginHolding Hold="Hold"/>
		<EndAvailable>994386.4704</EndAvailable>
		<EndHolding Hold="Hold"/>
	</DailyLog>
	<DailyLog date="2019-08-19">
		<date>2019-08-19</date>
		<BeginAvailable>994386.4704</BeginAvailable>
		<BeginHolding Hold="Hold"/>
		<BuyOperation>
			<StockCode>300664</StockCode>
			<StockNumber>37100</StockNumber>
			<CostPrice>13.38</CostPrice>
			<OtherExpenses>794.2368000000001</OtherExpenses>
			<Time>2019-08-19 10:28:44</Time>
		</BuyOperation>
		<EndAvailable>497194.2336</EndAvailable>
		<EndHolding Hold="Hold">
			<Stock>
				<StockCode>300664</StockCode>
				<StockNumber>37100</StockNumber>
				<CostPrice>13.38</CostPrice>
				<OtherExpenses>794.2368000000001</OtherExpenses>
			</Stock>
		</EndHolding>
	</DailyLog>
	<DailyLog date="2019-08-20">
		<date>2019-08-20</date>
		<BeginAvailable>497194.2336</BeginAvailable>
		<BeginHolding Hold="Hold">
			<Stock>
				<StockCode>300664</StockCode>
				<StockNumber>37100</StockNumber>
				<CostPrice>13.38</CostPrice>
				<OtherExpenses>794.2368000000001</OtherExpenses>
			</Stock>
		</BeginHolding>
		<BuyOperation>
			<StockCode>000910</StockCode>
			<StockNumber>47800</StockNumber>
			<CostPrice>10.65</CostPrice>
			<OtherExpenses>814.5120000000001</OtherExpenses>
			<Time>2019-08-20 14:12:49</Time>
		</BuyOperation>
		<SellOperation>
			<StockCode>300664</StockCode>
			<StockNumber>37100.0</StockNumber>
			<CostPrice>14.08</CostPrice>
			<OtherExpenses>0</OtherExpenses>
			<Time>2019-08-20 10:15:17</Time>
		</SellOperation>
		<EndAvailable>509677.72159999993</EndAvailable>
		<EndHolding Hold="Hold">
			<Stock>
				<StockCode>000910</StockCode>
				<StockNumber>47800</StockNumber>
				<CostPrice>10.65</CostPrice>
				<OtherExpenses>814.5120000000001</OtherExpenses>
			</Stock>
		</EndHolding>
	</DailyLog>
	<DailyLog date="2019-08-21">
		<date>2019-08-21</date>
		<BeginAvailable>509677.72159999993</BeginAvailable>
		<BeginHolding Hold="Hold">
			<Stock>
				<StockCode>000910</StockCode>
				<StockNumber>47800</StockNumber>
				<CostPrice>10.65</CostPrice>
				<OtherExpenses>814.5120000000001</OtherExpenses>
			</Stock>
		</BeginHolding>
		<SellOperation>
			<StockCode>000910</StockCode>
			<StockNumber>47800.0</StockNumber>
			<CostPrice>10.67</CostPrice>
			<OtherExpenses>0</OtherExpenses>
			<Time>2019-08-21 09:30:14</Time>
		</SellOperation>
		<EndAvailable>1019703.7215999999</EndAvailable>
		<EndHolding Hold="Hold"/>
	</DailyLog>
	<DailyLog date="2019-08-22">
		<date>2019-08-22</date>
		<BeginAvailable>1019703.7215999999</BeginAvailable>
		<BeginHolding Hold="Hold"/>
		<EndAvailable>1019703.7215999999</EndAvailable>
		<EndHolding Hold="Hold"/>
	</DailyLog>
	<DailyLog date="2019-08-23">
		<date>2019-08-23</date>
		<BeginAvailable>1019703.7215999999</BeginAvailable>
		<BeginHolding Hold="Hold"/>
		<EndAvailable>1019703.7215999999</EndAvailable>
		<EndHolding Hold="Hold"/>
	</DailyLog>
	<DailyLog date="2019-08-24">
		<date>2019-08-24</date>
		<BeginAvailable>1019703.7215999999</BeginAvailable>
		<BeginHolding Hold="Hold"/>
		<EndAvailable>1019703.7215999999</EndAvailable>
		<EndHolding Hold="Hold"/>
	</DailyLog>
</LogPack>
