<?xml version="1.0" encoding="utf-8"?>
<LogPack account="Account27">
	<Account number="Account27">
		<PassWord>123456</PassWord>
		<InitialFunds>1000000</InitialFunds>
	</Account>
	<DailyLog date="2019-01-01">
		<Date>2019-01-01</Date>
		<BeginAvailable>1000000</BeginAvailable>
		<BeginHolding>EmptyHold
		</BeginHolding>
		<EndAvailable>1000000</EndAvailable>
		<EndHolding>EmptyHold
		</EndHolding>
	</DailyLog>
	<DailyLog date="2019-08-11">
		<date>2019-08-11</date>
		<BeginAvailable>1000000.0</BeginAvailable>
		<BeginHolding Hold="Hold"/>
		<EndAvailable>1000000.0</EndAvailable>
		<EndHolding Hold="Hold"/>
	</DailyLog>
	<DailyLog date="2019-08-12">
		<date>2019-08-12</date>
		<BeginAvailable>1000000.0</BeginAvailable>
		<BeginHolding Hold="Hold"/>
		<EndAvailable>1000000.0</EndAvailable>
		<EndHolding Hold="Hold"/>
	</DailyLog>
	<DailyLog date="2019-08-13">
		<date>2019-08-13</date>
		<BeginAvailable>1000000.0</BeginAvailable>
		<BeginHolding Hold="Hold"/>
		<EndAvailable>1000000.0</EndAvailable>
		<EndHolding Hold="Hold"/>
	</DailyLog>
	<DailyLog date="2019-08-14">
		<date>2019-08-14</date>
		<BeginAvailable>1000000.0</BeginAvailable>
		<BeginHolding Hold="Hold"/>
		<EndAvailable>1000000.0</EndAvailable>
		<EndHolding Hold="Hold"/>
	</DailyLog>
	<DailyLog date="2019-08-15">
		<date>2019-08-15</date>
		<BeginAvailable>1000000.0</BeginAvailable>
		<BeginHolding Hold="Hold"/>
		<BuyOperation>
			<StockCode>002427</StockCode>
			<StockNumber>37000</StockNumber>
			<CostPrice>13.48</CostPrice>
			<OtherExpenses>798.0160000000001</OtherExpenses>
			<Time>2019-08-15 14:16:43</Time>
		</BuyOperation>
		<EndAvailable>500441.984</EndAvailable>
		<EndHolding Hold="Hold">
			<Stock>
				<StockCode>002427</StockCode>
				<StockNumber>37000</StockNumber>
				<CostPrice>13.48</CostPrice>
				<OtherExpenses>798.0160000000001</OtherExpenses>
			</Stock>
		</EndHolding>
	</DailyLog>
	<DailyLog date="2019-08-16">
		<date>2019-08-16</date>
		<BeginAvailable>500441.984</BeginAvailable>
		<BeginHolding Hold="Hold">
			<Stock>
				<StockCode>002427</StockCode>
				<StockNumber>37000</StockNumber>
				<CostPrice>13.48</CostPrice>
				<OtherExpenses>798.0160000000001</OtherExpenses>
			</Stock>
		</BeginHolding>
		<EndAvailable>500441.984</EndAvailable>
		<EndHolding Hold="Hold">
			<Stock>
				<StockCode>002427</StockCode>
				<StockNumber>37000.0</StockNumber>
				<CostPrice>13.48</CostPrice>
				<OtherExpenses>798.0160000000094</OtherExpenses>
			</Stock>
		</EndHolding>
	</DailyLog>
	<DailyLog date="2019-08-17">
		<date>2019-08-17</date>
		<BeginAvailable>500441.984</BeginAvailable>
		<BeginHolding Hold="Hold">
			<Stock>
				<StockCode>002427</StockCode>
				<StockNumber>37000</StockNumber>
				<CostPrice>13.48</CostPrice>
				<OtherExpenses>798.0160000000094</OtherExpenses>
			</Stock>
		</BeginHolding>
		<EndAvailable>500441.984</EndAvailable>
		<EndHolding Hold="Hold">
			<Stock>
				<StockCode>002427</StockCode>
				<StockNumber>37000.0</StockNumber>
				<CostPrice>13.48</CostPrice>
				<OtherExpenses>798.0160000000094</OtherExpenses>
			</Stock>
		</EndHolding>
	</DailyLog>
	<DailyLog date="2019-08-18">
		<date>2019-08-18</date>
		<BeginAvailable>500441.984</BeginAvailable>
		<BeginHolding Hold="Hold">
			<Stock>
				<StockCode>002427</StockCode>
				<StockNumber>37000</StockNumber>
				<CostPrice>13.48</CostPrice>
				<OtherExpenses>798.0160000000094</OtherExpenses>
			</Stock>
		</BeginHolding>
		<EndAvailable>500441.984</EndAvailable>
		<EndHolding Hold="Hold">
			<Stock>
				<StockCode>002427</StockCode>
				<StockNumber>37000.0</StockNumber>
				<CostPrice>13.48</CostPrice>
				<OtherExpenses>798.0160000000094</OtherExpenses>
			</Stock>
		</EndHolding>
	</DailyLog>
	<DailyLog date="2019-08-19">
		<date>2019-08-19</date>
		<BeginAvailable>500441.984</BeginAvailable>
		<BeginHolding Hold="Hold">
			<Stock>
				<StockCode>002427</StockCode>
				<StockNumber>37000</StockNumber>
				<CostPrice>13.48</CostPrice>
				<OtherExpenses>798.0160000000094</OtherExpenses>
			</Stock>
		</BeginHolding>
		<SellOperation>
			<StockCode>002427</StockCode>
			<StockNumber>37000.0</StockNumber>
			<CostPrice>11.94</CostPrice>
			<OtherExpenses>0</OtherExpenses>
			<Time>2019-08-19 09:30:32</Time>
		</SellOperation>
		<EndAvailable>942221.9839999999</EndAvailable>
		<EndHolding Hold="Hold"/>
	</DailyLog>
	<DailyLog date="2019-08-20">
		<date>2019-08-20</date>
		<BeginAvailable>942221.9839999999</BeginAvailable>
		<BeginHolding Hold="Hold"/>
		<EndAvailable>942221.9839999999</EndAvailable>
		<EndHolding Hold="Hold"/>
	</DailyLog>
	<DailyLog date="2019-08-21">
		<date>2019-08-21</date>
		<BeginAvailable>942221.9839999999</BeginAvailable>
		<BeginHolding Hold="Hold"/>
		<EndAvailable>942221.9839999999</EndAvailable>
		<EndHolding Hold="Hold"/>
	</DailyLog>
	<DailyLog date="2019-08-22">
		<date>2019-08-22</date>
		<BeginAvailable>942221.9839999999</BeginAvailable>
		<BeginHolding Hold="Hold"/>
		<BuyOperation>
			<StockCode>300207</StockCode>
			<StockNumber>36000</StockNumber>
			<CostPrice>13.08</CostPrice>
			<OtherExpenses>753.408</OtherExpenses>
			<Time>2019-08-22 10:51:08</Time>
		</BuyOperation>
		<EndAvailable>470588.57599999994</EndAvailable>
		<EndHolding Hold="Hold">
			<Stock>
				<StockCode>300207</StockCode>
				<StockNumber>36000</StockNumber>
				<CostPrice>13.08</CostPrice>
				<OtherExpenses>753.408</OtherExpenses>
			</Stock>
		</EndHolding>
	</DailyLog>
	<DailyLog date="2019-08-23">
		<date>2019-08-23</date>
		<BeginAvailable>470588.57599999994</BeginAvailable>
		<BeginHolding Hold="Hold">
			<Stock>
				<StockCode>300207</StockCode>
				<StockNumber>36000</StockNumber>
				<CostPrice>13.08</CostPrice>
				<OtherExpenses>753.408</OtherExpenses>
			</Stock>
		</BeginHolding>
		<EndAvailable>470588.57599999994</EndAvailable>
		<EndHolding Hold="Hold">
			<Stock>
				<StockCode>300207</StockCode>
				<StockNumber>36000.0</StockNumber>
				<CostPrice>13.08</CostPrice>
				<OtherExpenses>753.407999999986</OtherExpenses>
			</Stock>
		</EndHolding>
	</DailyLog>
	<DailyLog date="2019-08-24">
		<date>2019-08-24</date>
		<BeginAvailable>470588.57599999994</BeginAvailable>
		<BeginHolding Hold="Hold">
			<Stock>
				<StockCode>300207</StockCode>
				<StockNumber>36000</StockNumber>
				<CostPrice>13.08</CostPrice>
				<OtherExpenses>753.407999999986</OtherExpenses>
			</Stock>
		</BeginHolding>
		<EndAvailable>470588.57599999994</EndAvailable>
		<EndHolding Hold="Hold">
			<Stock>
				<StockCode>300207</StockCode>
				<StockNumber>36000.0</StockNumber>
				<CostPrice>13.08</CostPrice>
				<OtherExpenses>753.407999999986</OtherExpenses>
			</Stock>
		</EndHolding>
	</DailyLog>
</LogPack>
