<?xml version="1.0" encoding="utf-8"?>
<LogPack account="Account453">
	<Account number="Account453">
		<PassWord>123456</PassWord>
		<InitialFunds>1000000</InitialFunds>
	</Account>
	<DailyLog date="2019-01-01">
		<Date>2019-01-01</Date>
		<BeginAvailable>1000000</BeginAvailable>
		<BeginHolding>EmptyHold
		</BeginHolding>
		<EndAvailable>1000000</EndAvailable>
		<EndHolding>EmptyHold
		</EndHolding>
	</DailyLog>
	<DailyLog date="2019-08-05">
		<date>2019-08-05</date>
		<BeginAvailable>499592.62719999993</BeginAvailable>
		<BeginHolding Hold="Hold"/>
		<EndAvailable>499592.62719999993</EndAvailable>
		<EndHolding Hold="Hold">
			<Stock>
				<StockCode>300485</StockCode>
				<StockNumber>51400.0</StockNumber>
				<CostPrice>9.72</CostPrice>
				<OtherExpenses>799.372800000069</OtherExpenses>
			</Stock>
		</EndHolding>
	</DailyLog>
	<DailyLog date="2019-08-06">
		<date>2019-08-06</date>
		<BeginAvailable>499592.62719999993</BeginAvailable>
		<BeginHolding Hold="Hold">
			<Stock>
				<StockCode>300485</StockCode>
				<StockNumber>51400</StockNumber>
				<CostPrice>9.72</CostPrice>
				<OtherExpenses>799.372800000069</OtherExpenses>
			</Stock>
		</BeginHolding>
		<SellOperation>
			<StockCode>300485</StockCode>
			<StockNumber>51400.0</StockNumber>
			<CostPrice>9.5</CostPrice>
			<OtherExpenses>0</OtherExpenses>
			<Time>2019-08-06 09:29:27</Time>
		</SellOperation>
		<EndAvailable>987892.6272</EndAvailable>
		<EndHolding Hold="Hold">
			<Stock>
				<StockCode>300485</StockCode>
				<StockNumber>51400.0</StockNumber>
				<CostPrice>9.940000000000003</CostPrice>
				<OtherExpenses>1598.745600000138</OtherExpenses>
			</Stock>
		</EndHolding>
	</DailyLog>
</LogPack>
